[
    {
        "fullName": "24DCS120 RUTVI SHAH",
        "email": "shahrutvi020@gmail.com",
        "studentId": "24dcs120",
        "department": "computer-science",
        "year": "freshman",
        "registered_at": "2025-08-21 05:48:13"
    },
    {
        "fullName": "24DCS120 RUTVI SHAH",
        "email": "shahrutvi020@gmail.com",
        "studentId": "24dcs120",
        "department": "computer-science",
        "year": "sophomore",
        "registered_at": "2025-08-28 05:46:53"
    },
    {
        "fullName": "24DCS120 RUTVI SHAH",
        "email": "shahrutvi020@gmail.com",
        "studentId": "24dcs120",
        "department": "computer-science",
        "year": "freshman",
        "registered_at": "2025-08-28 06:32:48"
    }
]